gradefast/__init__.py
gradefast/__version__.py
gradefast/aggregate.py
gradefast/analyze.py
gradefast/command.py
gradefast/credentials.py
gradefast/evaluate.py
gradefast/exceptions.py
gradefast/gradefast.py
gradefast/group.py
gradefast/logconfig.py
gradefast/result.py
gradefast/submission.py
gradefast/test.py
gradefast/transform.py
gradefast/upload.py
gradefast/utils.py
gradefast-0.1.18.dist-info/LICENSE
gradefast-0.1.18.dist-info/METADATA
gradefast-0.1.18.dist-info/WHEEL
gradefast-0.1.18.dist-info/top_level.txt
gradefast-0.1.18.dist-info/RECORD
