Metadata-Version: 2.1
Name: gradefast
Version: 0.1.18
Summary: A framework that takes care of boundary tasks to ease task evaluations and make them faster.
Home-page: https://github.com/eyantra-eysip/GradeFast-2019
Author: Omkar Manjrekar
Author-email: manjrekarom@gmail.com
License: MIT
Platform: UNKNOWN
Classifier: License :: OSI Approved :: MIT License
Classifier: Programming Language :: Python
Classifier: Programming Language :: Python :: 3
Classifier: Programming Language :: Python :: 3.6
Classifier: Programming Language :: Python :: Implementation :: CPython
Classifier: Programming Language :: Python :: Implementation :: PyPy
Requires-Python: >=3.5.0
Requires-Dist: numpy
Requires-Dist: requests
Requires-Dist: beautifulsoup4
Requires-Dist: pandas
Requires-Dist: halo
Requires-Dist: python-slugify
